indeca-0.1.0.dist-info/METADATA
indeca-0.1.0.dist-info/WHEEL
indeca-0.1.0.dist-info/entry_points.txt
indeca-0.1.0.dist-info/licenses/LICENSE
indeca/AR_kernel.py
indeca/__init__.py
indeca/dashboard.py
indeca/deconv.py
indeca/logging_config.py
indeca/pipeline.py
indeca/simulation.py
indeca/utils.py
indeca-0.1.0.dist-info/RECORD
