Metadata-Version: 2.1
Name: indeca
Version: 0.1.0
Author: phildong
License: GPL-3.0
Requires-Python: <3.13,>=3.11
Requires-Dist: numpy<2
Requires-Dist: pandas>=2.2.3
Requires-Dist: plotly>=6.0.0
Requires-Dist: seaborn>=0.13.2
Requires-Dist: xarray>=2025.1.2
Requires-Dist: scipy>=1.15.2
Requires-Dist: tqdm>=4.67.1
Requires-Dist: opencv-python>=4.11.0.86
Requires-Dist: python-levenshtein>=0.26.1
Requires-Dist: dask>=2025.2.0
Requires-Dist: cvxpy==1.5.1
Requires-Dist: scikit-learn>=1.6.1
Requires-Dist: statsmodels>=0.14.4
Requires-Dist: distributed>=2025.2.0
Requires-Dist: netcdf4>=1.7.2
Requires-Dist: pyarrow>=19.0.1
Requires-Dist: dtaidistance>=2.3.12
Requires-Dist: osqp>=0.6.7.post3
Requires-Dist: panel>=1.5.5
Requires-Dist: sparse>=0.15.5
Requires-Dist: line-profiler>=4.1.3
Requires-Dist: scikit-image>=0.25.2
